AUTHORS.rst
CHANGELOG.rst
CONTRIBUTING.rst
MANIFEST.in
README.rst
requirements.txt
setup.py
docs/authors.rst
docs/changelog.rst
docs/contributing.rst
docs/example_usage.rst
docs/getting_started.rst
docs/index.rst
docs/proteofav_docs.rst
docs/readme.rst
proteofav/__init__.py
proteofav/annotation.py
proteofav/config.ini
proteofav/config.py
proteofav/dssp.py
proteofav/library.py
proteofav/main.py
proteofav/mergers.py
proteofav/msas.py
proteofav/sifts.py
proteofav/structures.py
proteofav/utils.py
proteofav/validation.py
proteofav/variants.py
proteofav/visualise.py
proteofav.egg-info/PKG-INFO
proteofav.egg-info/SOURCES.txt
proteofav.egg-info/dependency_links.txt
proteofav.egg-info/entry_points.txt
proteofav.egg-info/requires.txt
proteofav.egg-info/top_level.txt
tests/__init__.py
tests/test_annotation.py
tests/test_config.py
tests/test_dssp.py
tests/test_mergers.py
tests/test_msas.py
tests/test_sifts.py
tests/test_structures.py
tests/test_utils.py
tests/test_validation.py
tests/test_variants.py
tests/test_visualise.py