Metadata-Version: 1.1
Name: proteofav
Version: 0.2.3
Summary: PROtein Feature Aggregation and Variants.
Home-page: https://github.com/bartongroup/ProteoFAV/tree/master
Author: ['Fábio Madeira', 'Thiago Britto-Borges', 'Stuart MacGowan']
Author-email: tbrittoborges@dundee.ac.uk
License: LICENSE.md
Download-URL: https://github.com/bartongroup/ProteoFAV/archive/master.zip
Keywords: bioinformatics structural-biology data-analysis python pandas
Platform: UNKNOWN
Classifier: Development Status :: 4 - Beta
Classifier: Intended Audience :: Developers
Classifier: Intended Audience :: Science/Research
Classifier: Natural Language :: English
Classifier: Programming Language :: Python :: 3.5
Classifier: Programming Language :: Python :: 3.6
Classifier: Programming Language :: Python :: Implementation :: PyPy
Classifier: Topic :: Internet
Classifier: Topic :: Scientific/Engineering :: Bio-Informatics
Classifier: Topic :: Software Development :: Libraries :: Python Modules
Classifier: License :: OSI Approved :: MIT License
